kick_off/__init__.py
kick_off/__main__.py
kick_off/conf.py
kick_off/core.py
kick_off/cprint.py
kick_off/initializer.py
kick_off/normalizer.py
kick_off/files/.editorconfig
kick_off/files/settings.py
kick_off/files/core/urls.py
kick_off/files/home/context_processors.py
kick_off/files/home/urls.py
kick_off/files/home/views.py
kick_off/files/home/static/favicon.ico
kick_off/files/home/templates/home/main.html
kick_off/scripts/__init__.py
kick_off/scripts/installers.py
django_kick_off-0.0.4.dist-info/LICENSE.txt
django_kick_off-0.0.4.dist-info/METADATA
django_kick_off-0.0.4.dist-info/WHEEL
django_kick_off-0.0.4.dist-info/top_level.txt
django_kick_off-0.0.4.dist-info/RECORD
