Metadata-Version: 2.1
Name: django-kick-off
Version: 0.0.4
Summary: Start a virtual environment and a fully configurated Django project with an app
Home-page: https://github.com/ignacio-nava/django-kick-off
Author: Ignacio Nava
Author-email: nava_ignacio@outlook.com
License: UNKNOWN
Platform: UNKNOWN
Classifier: Environment :: Console
Classifier: Programming Language :: Python :: 3.6
Classifier: Programming Language :: Python :: 3.7
Classifier: Programming Language :: Python :: 3.8
Classifier: Programming Language :: Python :: 3.9
Classifier: License :: OSI Approved :: MIT License
Classifier: Operating System :: MacOS
Classifier: Topic :: Software Development
Requires-Python: >=3.6
Provides-Extra: dev
Requires-Dist: pytest (>=3.6) ; extra == 'dev'
Requires-Dist: check-manifest ; extra == 'dev'
